jollyjack/__init__.py
jollyjack/cjollyjack.pxd
jollyjack/direct_reader.h
jollyjack/io_uring_reader_1.h
jollyjack/jollyjack.h
jollyjack/jollyjack_cython.cpython-314t-x86_64-linux-gnu.so
jollyjack/jollyjack_cython.pyi
jollyjack/jollyjack_cython.pyx
jollyjack/package_metadata.py
jollyjack/read_into_memory_io_uring.h
jollyjack.libs/liburing-2907b6bc.so.1.0.7
jollyjack-0.20.3.dist-info/METADATA
jollyjack-0.20.3.dist-info/WHEEL
jollyjack-0.20.3.dist-info/top_level.txt
jollyjack-0.20.3.dist-info/RECORD
jollyjack-0.20.3.dist-info/licenses/LICENSE
jollyjack-0.20.3.dist-info/sboms/auditwheel.cdx.json
