Metadata-Version: 2.4
Name: jollyjack
Version: 0.20.3
Summary: Read parquet data directly into numpy array
Project-URL: Homepage, https://github.com/marcin-krystianc/jollyjack
Project-URL: Issues, https://github.com/marcin-krystianc/jollyjack/issues
Classifier: Programming Language :: Python :: 3
Classifier: License :: OSI Approved :: Apache Software License
Classifier: Operating System :: OS Independent
Requires-Python: >=3.9
License-File: LICENSE
Requires-Dist: pyarrow~=22.0.0
Requires-Dist: numpy>=1.16.6
Dynamic: license-file
